LICENSE
MANIFEST.in
README.md
setup.py
oauth_dropins/__init__.py
oauth_dropins/blogger.py
oauth_dropins/blogger_v2.py
oauth_dropins/bluesky.py
oauth_dropins/disqus.py
oauth_dropins/dropbox.py
oauth_dropins/facebook.py
oauth_dropins/flickr.py
oauth_dropins/flickr_auth.py
oauth_dropins/github.py
oauth_dropins/google_signin.py
oauth_dropins/indieauth.py
oauth_dropins/instagram.py
oauth_dropins/linkedin.py
oauth_dropins/mastodon.py
oauth_dropins/medium.py
oauth_dropins/meetup.py
oauth_dropins/models.py
oauth_dropins/pixelfed.py
oauth_dropins/reddit.py
oauth_dropins/threads.py
oauth_dropins/tumblr.py
oauth_dropins/twitter.py
oauth_dropins/twitter_auth.py
oauth_dropins/twitter_v2.py
oauth_dropins/views.py
oauth_dropins/wordpress_rest.py
oauth_dropins.egg-info/PKG-INFO
oauth_dropins.egg-info/SOURCES.txt
oauth_dropins.egg-info/dependency_links.txt
oauth_dropins.egg-info/requires.txt
oauth_dropins.egg-info/top_level.txt
oauth_dropins/fonts/glyphicons-halflings-regular.eot
oauth_dropins/fonts/glyphicons-halflings-regular.svg
oauth_dropins/fonts/glyphicons-halflings-regular.ttf
oauth_dropins/fonts/glyphicons-halflings-regular.woff
oauth_dropins/fonts/glyphicons-halflings-regular.woff2
oauth_dropins/static/appengine_button_noborder.gif
oauth_dropins/static/atproto_2x.png
oauth_dropins/static/atproto_large.png
oauth_dropins/static/blogger.png
oauth_dropins/static/blogger_2x.png
oauth_dropins/static/blogger_button.png
oauth_dropins/static/blogger_full.png
oauth_dropins/static/blogger_icon.png
oauth_dropins/static/bluesky.svg
oauth_dropins/static/bluesky_icon.png
oauth_dropins/static/bluesky_logo.png
oauth_dropins/static/bluesky_logotype.png
oauth_dropins/static/bootstrap-theme.min.css
oauth_dropins/static/bootstrap.min.css
oauth_dropins/static/continue_with_facebook_2x.png
oauth_dropins/static/disqus.png
oauth_dropins/static/disqus_2x.png
oauth_dropins/static/disqus_full.png
oauth_dropins/static/dropbox.png
oauth_dropins/static/dropbox_2x.png
oauth_dropins/static/dropbox_full.png
oauth_dropins/static/dropbox_full.svg
oauth_dropins/static/facebook.png
oauth_dropins/static/facebook_2x.png
oauth_dropins/static/facebook_button.png
oauth_dropins/webutil/webutil.egg-info/PKG-INFO
oauth_dropins/webutil/webutil.egg-info/SOURCES.txt
oauth_dropins/webutil/webutil.egg-info/dependency_links.txt
oauth_dropins/webutil/webutil.egg-info/requires.txt
oauth_dropins/webutil/webutil.egg-info/top_level.txt