Metadata-Version: 2.1
Name: oauth-dropins
Version: 6.8
Summary: Drop-in OAuth Flask views for many popular sites.
Home-page: https://github.com/snarfed/oauth-dropins
Author: Ryan Barrett
Author-email: oauth-dropins@ryanb.org
License: Public domain
Keywords: oauth appengine
Classifier: Development Status :: 5 - Production/Stable
Classifier: Intended Audience :: Developers
Classifier: Topic :: System :: Systems Administration :: Authentication/Directory
Classifier: Topic :: Software Development :: Libraries :: Python Modules
Classifier: Environment :: Web Environment
Classifier: License :: OSI Approved :: MIT License
Classifier: License :: Public Domain
Classifier: Programming Language :: Python :: 3
Classifier: Programming Language :: Python :: 3.7
Classifier: Programming Language :: Python :: 3.8
Classifier: Programming Language :: Python :: 3.9
Requires-Python: >=3.7
License-File: LICENSE
Requires-Dist: arroba>=0.4
Requires-Dist: beautifulsoup4>=4.8
Requires-Dist: cachetools>=3.1
Requires-Dist: cryptography>=2.0
Requires-Dist: domain2idna>=1.12
Requires-Dist: flask>=2.0.1
Requires-Dist: flask-caching>=1.10.1
Requires-Dist: gdata-python3>=3.0
Requires-Dist: google-cloud-ndb>=1.10.1
Requires-Dist: humanize>=3.1.0
Requires-Dist: jinja2>=2.10
Requires-Dist: lexrpc>=1.1
Requires-Dist: mf2py>=1.1
Requires-Dist: mf2util>=0.5.0
Requires-Dist: oauthlib>=3.1
Requires-Dist: pkce>=1.0.3
Requires-Dist: praw>=7.3.0
Requires-Dist: python-tumblpy>=1.1
Requires-Dist: requests-oauth2client>=1.6.0
Requires-Dist: requests-oauthlib
Requires-Dist: requests>=2.22
Requires-Dist: tweepy>=4.5
Requires-Dist: ujson>=5.1
Requires-Dist: urllib3>=1.14
Provides-Extra: docs
Requires-Dist: sphinx; extra == "docs"
Requires-Dist: sphinx-rtd-theme; extra == "docs"
